{
  "$schema": "https://json-schema.org/draft/2020-12/schema",
  "title": "region_state.json",
  "type": "object",
  "additionalProperties": false,
  "required": ["regions"],
  "properties": {
    "regions": {
      "type": "array",
      "items": {
        "type": "object",
        "additionalProperties": false,
        "required": ["base", "id", "owner", "prot", "size"],
        "properties": {
          "base":  { "type": "integer", "minimum": 0 },
          "id":    { "type": "string" },
          "owner": { "type": "string" },
          "prot":  { "type": "string", "enum": ["r", "rw", "rx", "rwx"] },
          "size":  { "type": "integer", "minimum": 1 }
        }
      }
    }
  }
}
